qikdb/__init__.py
qikdb-4.0.1.dist-info/WHEEL
qikdb-4.0.1.dist-info/METADATA
qikdb-4.0.1.dist-info/RECORD
